.gitignore
CMakeLists.txt
LICENSE.md
README.md
VTKViewer.cxx
VTKViewer.h
bld.bat
build.sh
main.cxx
meta.yaml
posix_build.sh
setup.cfg
setup.py
vtkviewer.py
vtkviewer.egg-info/PKG-INFO
vtkviewer.egg-info/SOURCES.txt
vtkviewer.egg-info/dependency_links.txt
vtkviewer.egg-info/pbr.json
vtkviewer.egg-info/top_level.txt